README.txt
setup.cfg
setup.py
cs/__init__.py
cs.discussionextender.egg-info/PKG-INFO
cs.discussionextender.egg-info/SOURCES.txt
cs.discussionextender.egg-info/dependency_links.txt
cs.discussionextender.egg-info/entry_points.txt
cs.discussionextender.egg-info/namespace_packages.txt
cs.discussionextender.egg-info/not-zip-safe
cs.discussionextender.egg-info/paster_plugins.txt
cs.discussionextender.egg-info/requires.txt
cs.discussionextender.egg-info/top_level.txt
cs/discussionextender/__init__.py
cs/discussionextender/comments.pt
cs/discussionextender/comments.py
cs/discussionextender/configure.zcml
cs/discussionextender/discussion.py
cs/discussionextender/rebuild_i18n.sh
cs/discussionextender/tests.py
cs/discussionextender/locales/cs.discussionextender-manual.pot
cs/discussionextender/locales/cs.discussionextender.pot
cs/discussionextender/locales/es/LC_MESSAGES/cs.discussionextender.po
cs/discussionextender/locales/eu/LC_MESSAGES/cs.discussionextender.po
docs/HISTORY.txt
docs/INSTALL.txt
docs/LICENSE.GPL
docs/LICENSE.txt