Metadata-Version: 1.1
Name: cs.discussionextender
Version: 1.0.4
Summary: This product extends plone.app.discussion's from with 2 extra fields: email and url
Home-page: http://github.com/codesyntax/cs.discussionextender
Author: Mikel Larreategi
Author-email: mlarreategi@codesyntax.com
License: GPL
Keywords: discussion extender
Platform: UNKNOWN
Classifier: Framework :: Plone
Classifier: Programming Language :: Python
